[
  {
    "thumbnail": "../../assets/images/weteka.png",
    "title": "How to use Weteka?",
    "org": {
      "name": "Weteka",
      "logo": "../assets/images/koompi.webp",
      "is_verify": true
    },
    "viewer": "1200",
    "created_at": "20230607",
    "is_free": true,
    "pricing": "0",
    "is_enrollment": true,
    "progress": 0
  },
  {
    "thumbnail": "../assets/images/weteka.png",
    "title": "How to use Weteka?",
    "org": {
      "name": "Weteka",
      "logo": "../assets/images/koompi.webp",
      "is_verify": true
    },
    "viewer": "1200",
    "created_at": "20230607",
    "is_free": false,
    "pricing": "15",
    "is_enrollment": true,
    "progress": 0
  },
  {
    "thumbnail": "../assets/images/weteka.png",
    "title": "How to use Weteka?",
    "org": {
      "name": "Weteka",
      "logo": "../assets/images/koompi.webp",
      "is_verify": true
    },
    "viewer": "1200",
    "created_at": "20230607",
    "is_free": false,
    "pricing": "15",
    "is_enrollment": true,
    "progress": 0
  },
  {
    "thumbnail": "../assets/images/weteka.png",
    "title": "How to use Weteka?",
    "org": {
      "name": "Weteka",
      "logo": "../assets/images/koompi.webp",
      "is_verify": true
    },
    "viewer": "1200",
    "created_at": "20230607",
    "is_free": true,
    "pricing": "0",
    "is_enrollment": true,
    "progress": 0
  },
  {
    "thumbnail": "../assets/images/weteka.png",
    "title": "How to use Weteka?",
    "org": {
      "name": "Weteka",
      "logo": "../assets/images/koompi.webp",
      "is_verify": true
    },
    "viewer": "1200",
    "created_at": "20230607",
    "is_free": false,
    "pricing": "15",
    "is_enrollment": false,
    "progress": 0
  },
  {
    "thumbnail": "../assets/images/weteka.png",
    "title": "How to use Weteka?",
    "org": {
      "name": "Weteka",
      "logo": "../assets/images/koompi.webp",
      "is_verify": true
    },
    "viewer": "1200",
    "created_at": "20230607",
    "is_free": true,
    "pricing": "0",
    "is_enrollment": false,
    "progress": 0
  },
  {
    "thumbnail": "../assets/images/weteka.png",
    "title": "How to use Weteka?",
    "org": {
      "name": "Weteka",
      "logo": "../assets/images/koompi.webp",
      "is_verify": true
    },
    "viewer": "1200",
    "created_at": "20230607",
    "is_free": true,
    "pricing": "0",
    "is_enrollment": false,
    "progress": 0
  },
  {
    "thumbnail": "../assets/images/weteka.png",
    "title": "How to use Weteka?",
    "org": {
      "name": "Weteka",
      "logo": "../assets/images/koompi.webp",
      "is_verify": true
    },
    "viewer": "1200",
    "created_at": "20220607",
    "is_free": false,
    "pricing": "15",
    "is_enrollment": false,
    "progress": 0
  }
]
